<annotation>
	<folder>maggi</folder>
	<filename>maggi0262.jpg</filename>
	<path>/home/hanming2805/datasets/images/maggi/maggi0262.jpg</path>
	<source>
		<database>Unknown</database>
	</source>
	<size>
		<width>480</width>
		<height>640</height>
		<depth>3</depth>
	</size>
	<segmented>0</segmented>
	<object>
		<name>maggi</name>
		<pose>Unspecified</pose>
		<truncated>0</truncated>
		<difficult>0</difficult>
		<bndbox>
			<xmin>120</xmin>
			<ymin>200</ymin>
			<xmax>309</xmax>
			<ymax>436</ymax>
		</bndbox>
	</object>
</annotation>
